owo/__init__.py
owo/__main__.py
owo/aiohttp2.py
owo/async_owo.py
owo/bg.py
owo/cli.py
owo/fix_termux.py
owo/owo.py
owo/utils.py
owo-2.2.2.dist-info/DESCRIPTION.rst
owo-2.2.2.dist-info/METADATA
owo-2.2.2.dist-info/RECORD
owo-2.2.2.dist-info/WHEEL
owo-2.2.2.dist-info/entry_points.txt
owo-2.2.2.dist-info/metadata.json
owo-2.2.2.dist-info/top_level.txt
