Metadata-Version: 2.0
Name: owo
Version: 2.2.2
Summary: Python API wrapper for api.awau.moe
Home-page: https://github.com/whats-this/owo.py
Author: martmists
Author-email: martmists@gmail.com
License: MIT
Keywords: api wrapper owo
Platform: UNKNOWN
Classifier: Development Status :: 5 - Production/Stable
Classifier: Intended Audience :: Developers
Classifier: Natural Language :: English
Classifier: Operating System :: OS Independent
Classifier: Topic :: Communications :: File Sharing
Classifier: License :: OSI Approved :: MIT License
Classifier: Programming Language :: Python :: 2.7
Classifier: Programming Language :: Python :: 3.4
Requires-Python: >=2.0,>=3.0
Requires-Dist: requests
